<?xml version="1.0" encoding="UTF-8"?>
<assessmentTest
  xmlns="http://www.imsglobal.org/xsd/imsqti_v2p1"
  xmlns:xsi="http://www.w3.org/2001/XMLSchema-instance"
  xsi:schemaLocation="http://www.imsglobal.org/xsd/imsqti_v2p1 imsqti_v2p1.xsd"
  identifier="My_Intervention"
  title="My Intervention">
  <outcomeDeclaration identifier="q1" cardinality="single" baseType="float"/>
  <outcomeDeclaration identifier="q2" cardinality="single" baseType="float"/>
  <testPart identifier="My_Intervention-part1" navigationMode="linear" submissionMode="individual">
    <assessmentSection identifier="My_Intervention-section1" title="My_Intervention-section1" visible="true">
      <assessmentItemRef identifier="page2demo" href="page2demo.xml"/>
      <assessmentItemRef identifier="dummypage" href="dummypage.xml"/>
    </assessmentSection>
  </testPart>
  <outcomeProcessing/>
</assessmentTest>